streamlit_query_wrapper/__init__.py
streamlit_query_wrapper/query_wrapper.py
streamlit_query_wrapper-0.1.3.dist-info/LICENSE
streamlit_query_wrapper-0.1.3.dist-info/METADATA
streamlit_query_wrapper-0.1.3.dist-info/WHEEL
streamlit_query_wrapper-0.1.3.dist-info/top_level.txt
streamlit_query_wrapper-0.1.3.dist-info/RECORD
