Metadata-Version: 2.1
Name: streamlit-query-wrapper
Version: 0.1.3
Summary: A wrapper for Streamlit components accessable via query parameters
Home-page: https://github.com/minolee/streamlit_query_wrapper
Author: Minho Lee
Author-email: Minho Lee <lmh30002@gmail.com>
Maintainer-email: Minho Lee <lmh30002@gmail.com>
Project-URL: Homepage, https://github.com/minolee/streamlit_query_wrapper
Classifier: Programming Language :: Python :: 3.10
Classifier: Programming Language :: Python :: 3.11
Classifier: Programming Language :: Python :: 3.12
Requires-Python: >=3.10
License-File: LICENSE
Requires-Dist: streamlit
